ldotel/__init__.py
ldotel/testing/__init__.py
ldotel/testing/test_tracing.py
ldotel/tracing.py
launchdarkly_server_sdk_otel-1.1.0.dist-info/LICENSE.txt
launchdarkly_server_sdk_otel-1.1.0.dist-info/METADATA
launchdarkly_server_sdk_otel-1.1.0.dist-info/WHEEL
launchdarkly_server_sdk_otel-1.1.0.dist-info/RECORD
