Metadata-Version: 2.3
Name: launchdarkly-server-sdk-otel
Version: 1.1.0
Summary: LaunchDarkly SDK OpenTelemetry integration
License: Apache-2.0
Author: LaunchDarkly
Author-email: dev@launchdarkly.com
Requires-Python: >=3.9
Classifier: Intended Audience :: Developers
Classifier: License :: OSI Approved :: Apache Software License
Classifier: Operating System :: OS Independent
Classifier: Programming Language :: Python :: 3
Classifier: Programming Language :: Python :: 3.9
Classifier: Programming Language :: Python :: 3.10
Classifier: Programming Language :: Python :: 3.11
Classifier: Programming Language :: Python :: 3.12
Classifier: Programming Language :: Python :: 3.13
Classifier: Topic :: Software Development
Classifier: Topic :: Software Development :: Libraries
Requires-Dist: launchdarkly-server-sdk (>=9.4.0)
Requires-Dist: opentelemetry-sdk (>=1.24.0)
Project-URL: Documentation, https://launchdarkly-python-sdk-otel-integration.readthedocs.io/en/latest/
Project-URL: Homepage, https://docs.launchdarkly.com/sdk/server-side/python
Project-URL: Repository, https://github.com/launchdarkly/python-server-sdk-otel
